.gitignore
.gitmodules
.nojekyll
Makefile
README.md
index.html
setup.py
docs/Connecting_A_Client.rst
docs/conf.py
docs/index.rst
docs/make.bat
docs/python_sikuli_client.asserts.rst
docs/python_sikuli_client.classes.rst
docs/python_sikuli_client.exceptions.rst
docs/python_sikuli_client.finder.rst
docs/python_sikuli_client.globals.rst
docs/python_sikuli_client.location.rst
docs/python_sikuli_client.match.rst
docs/python_sikuli_client.misc.rst
docs/python_sikuli_client.pattern.rst
docs/python_sikuli_client.region.rst
docs/python_sikuli_client.rst
docs/python_sikuli_client.screen.rst
docs/python_sikuli_client.sikuli_class.rst
docs/python_sikuli_client.sikuli_client.rst
docs/regen.py
src/python_sikuli_client/Consts.py
src/python_sikuli_client/__init__.py
src/python_sikuli_client/asserts.py
src/python_sikuli_client/classes.py
src/python_sikuli_client/exceptions.py
src/python_sikuli_client/finder.py
src/python_sikuli_client/globals.py
src/python_sikuli_client/keywords.json
src/python_sikuli_client/location.py
src/python_sikuli_client/match.py
src/python_sikuli_client/misc.py
src/python_sikuli_client/pattern.py
src/python_sikuli_client/region.py
src/python_sikuli_client/screen.py
src/python_sikuli_client/sikuli_class.py
src/python_sikuli_client/sikuli_client.py
src/python_sikuli_client/version
src/python_sikuli_client.egg-info/PKG-INFO
src/python_sikuli_client.egg-info/SOURCES.txt
src/python_sikuli_client.egg-info/dependency_links.txt
src/python_sikuli_client.egg-info/requires.txt
src/python_sikuli_client.egg-info/top_level.txt