Metadata-Version: 1.1
Name: python-sikuli-client
Version: 0.1.9
Summary: Python library to act as a client for jython-sikuli-server
Home-page: https://github.com/alistair-broomhead/python-sikuli-client
Author: Alistair Broomhead
Author-email: alistair.broomhead@gmail.com
License: MIT
Download-URL: https://github.com/alistair-broomhead/python-sikuli-client/zipball/master
Platform: UNKNOWN
